<?xml version="1.0" encoding="UTF-8"?>
<eventSheets layout="MainScene" previous="" next="" version="2.0">
  <item type="instance" UID="4543"/>
  <item type="instance" UID="4394">
    <item type="behavior" behaviorType="FlashBehavior" name="闪烁">
      <item valueDataType="any" value="0.3" name="onTime"/>
      <item valueDataType="any" value="0.1" name="offTime"/>
      <item valueDataType="any" value="0" name="times"/>
      <item valueDataType="any" value="1" name="enabled"/>
    </item>
  </item>
  <item type="instance" UID="4023"/>
  <item type="instance" UID="4029"/>
  <item type="instance" UID="4032"/>
  <item type="instance" UID="4035"/>
  <item type="instance" UID="4038"/>
  <item type="instance" UID="4062"/>
  <item type="instance" UID="4385"/>
  <item type="instance" UID="4017"/>
  <item type="instance" UID="4014"/>
  <item type="instance" UID="4011"/>
  <item type="instance" UID="4008"/>
  <item type="instance" UID="4005"/>
  <item type="instance" UID="3984"/>
  <item type="instance" UID="3978"/>
  <item type="instance" UID="3981"/>
  <item type="instance" UID="3987"/>
  <item type="instance" UID="4104"/>
  <item type="instance" UID="4111"/>
  <item type="instance" UID="4118"/>
  <item type="instance" UID="4133"/>
  <item type="instance" UID="4140"/>
  <item type="instance" UID="4149"/>
  <item type="instance" UID="4246"/>
  <item type="instance" UID="16">
    <item initValue="0" variableType="number" variableName="one" type="variable"/>
    <item type="behavior" behaviorType="DragDropBehaivor" name="拖拽">
      <item valueDataType="any" value="0" name="axes"/>
      <item valueDataType="any" value="1" name="enabled"/>
    </item>
  </item>
  <item type="instance" UID="4041">
    <item type="behavior" behaviorType="FlashBehavior" name="闪烁">
      <item valueDataType="any" value="0.1" name="onTime"/>
      <item valueDataType="any" value="0.1" name="offTime"/>
      <item valueDataType="any" value="0" name="times"/>
      <item valueDataType="any" value="1" name="enabled"/>
    </item>
  </item>
  <item type="instance" UID="4525"/>
  <item type="event" conditionRelationShip="true" triggerOnceWhileTrue="false">
    <item type="condition" callTarget="instance" paramsClass="IsButtonDownEvent" callName="isTouchDown" isTrigger="false" target="TT1"/>
    <item type="action" callTarget="instance" callName="play" target="TouchDown">
      <item valueDataType="any" value="1" name="2"/>
      <item valueDataType="any" value="1" name="3"/>
    </item>
    <item type="action" callTarget="instance" callName="setValue" target="pane">
      <item valueDataType="string" value="one" name="10" variable="true"/>
      <item valueDataType="any" value="1" name="11"/>
    </item>
    <item type="action" callTarget="instance" callName="setPosition" target="baZii">
      <item valueDataType="any" value="324.03" name="16"/>
      <item valueDataType="any" value="253.07" name="17"/>
    </item>
    <item type="action" callTarget="instance" callName="destory" target="TT1"/>
    <item type="action" callTarget="instance" callName="setPosition" target="F1">
      <item valueDataType="any" value="253.62" name="16"/>
      <item valueDataType="any" value="172.62" name="17"/>
    </item>
    <item type="action" callTarget="instance" callName="setEnabled" target="TT2">
      <item valueDataType="any" value="1" name="14"/>
    </item>
  </item>
  <item type="event" conditionRelationShip="true" triggerOnceWhileTrue="false">
    <item type="condition" callTarget="instance" paramsClass="OnSceneInitCompleteEvent" callName="onSceneInitComplete" isTrigger="true" target="System"/>
    <item type="action" callTarget="instance" callName="setVisible" target="textA">
      <item valueDataType="any" value="0" name="10"/>
    </item>
    <item type="action" callTarget="instance" callName="setVisible" target="textB">
      <item valueDataType="any" value="0" name="10"/>
    </item>
    <item type="action" callTarget="instance" callName="setVisible" target="textC">
      <item valueDataType="any" value="0" name="10"/>
    </item>
    <item type="action" callTarget="instance" callName="setVisible" target="textD">
      <item valueDataType="any" value="0" name="10"/>
    </item>
    <item type="action" callTarget="instance" callName="setEnabled" target="TT2">
      <item valueDataType="any" value="0" name="14"/>
    </item>
    <item type="action" callTarget="instance" callName="setEnabled" target="TT3">
      <item valueDataType="any" value="0" name="14"/>
    </item>
    <item type="action" callTarget="instance" callName="setEnabled" target="TT4">
      <item valueDataType="any" value="0" name="14"/>
    </item>
    <item type="action" callTarget="instance" callName="setEnabled" target="TT5">
      <item valueDataType="any" value="0" name="14"/>
    </item>
    <item type="action" callTarget="instance" callName="setEnabled" target="TT6">
      <item valueDataType="any" value="0" name="14"/>
    </item>
  </item>
  <item type="event" conditionRelationShip="true" triggerOnceWhileTrue="false">
    <item type="condition" callTarget="instance" paramsClass="IsButtonDownEvent" callName="isTouchDown" isTrigger="false" target="TT2"/>
    <item type="action" callTarget="instance" callName="play" target="TouchDown">
      <item valueDataType="any" value="1" name="2"/>
      <item valueDataType="any" value="1" name="3"/>
    </item>
    <item type="action" callTarget="instance" callName="setValue" target="pane">
      <item valueDataType="string" value="one" name="10" variable="true"/>
      <item valueDataType="any" value="2" name="11"/>
    </item>
    <item type="action" callTarget="instance" callName="setPosition" target="baZii">
      <item valueDataType="any" value="280.09" name="16"/>
      <item valueDataType="any" value="323.82" name="17"/>
    </item>
    <item type="action" callTarget="instance" callName="spawn" target="pane">
      <item valueDataType="string" value="drawR" name="10" isFamily="false"/>
      <item valueDataType="any" value="0" name="11"/>
      <item valueDataType="any" value="-30" name="12"/>
      <item valueDataType="any" value="-30" name="13"/>
      <item valueDataType="any" value="0" name="14"/>
    </item>
    <item type="action" callTarget="instance" callName="rotateClockWise" target="drawR">
      <item valueDataType="any" value="189" name="10"/>
    </item>
    <item type="action" callTarget="instance" callName="destory" target="TT2"/>
    <item type="action" callTarget="instance" callName="setPosition" target="F2">
      <item valueDataType="any" value="313.34" name="16"/>
      <item valueDataType="any" value="275.10" name="17"/>
    </item>
    <item type="action" callTarget="instance" callName="setEnabled" target="TT3">
      <item valueDataType="any" value="1" name="14"/>
    </item>
  </item>
  <item type="event" conditionRelationShip="true" triggerOnceWhileTrue="false">
    <item type="condition" callTarget="instance" paramsClass="IsButtonDownEvent" callName="isTouchDown" isTrigger="false" target="TT3"/>
    <item type="action" callTarget="instance" callName="play" target="TouchDown">
      <item valueDataType="any" value="1" name="2"/>
      <item valueDataType="any" value="1" name="3"/>
    </item>
    <item type="action" callTarget="instance" callName="setValue" target="pane">
      <item valueDataType="string" value="one" name="10" variable="true"/>
      <item valueDataType="any" value="3" name="11"/>
    </item>
    <item type="action" callTarget="instance" callName="setPosition" target="baZii">
      <item valueDataType="any" value="360.09" name="16"/>
      <item valueDataType="any" value="274.82" name="17"/>
    </item>
    <item type="action" callTarget="instance" callName="setPosition" target="drawRt">
      <item valueDataType="any" value="300" name="16"/>
      <item valueDataType="any" value="310" name="17"/>
    </item>
    <item type="action" callTarget="instance" callName="rotateClockWise" target="drawRt">
      <item valueDataType="any" value="11" name="10"/>
    </item>
    <item type="action" callTarget="instance" callName="destory" target="TT3"/>
    <item type="action" callTarget="instance" callName="setPosition" target="F3">
      <item valueDataType="any" value="290.97" name="16"/>
      <item valueDataType="any" value="341.32" name="17"/>
    </item>
    <item type="action" callTarget="instance" callName="setEnabled" target="TT4">
      <item valueDataType="any" value="1" name="14"/>
    </item>
  </item>
  <item type="event" conditionRelationShip="true" triggerOnceWhileTrue="false">
    <item type="condition" callTarget="instance" paramsClass="IsButtonDownEvent" callName="isTouchDown" isTrigger="false" target="TT4"/>
    <item type="action" callTarget="instance" callName="play" target="TouchDown">
      <item valueDataType="any" value="1" name="2"/>
      <item valueDataType="any" value="1" name="3"/>
    </item>
    <item type="action" callTarget="instance" callName="setValue" target="pane">
      <item valueDataType="string" value="one" name="10" variable="true"/>
      <item valueDataType="any" value="4" name="11"/>
    </item>
    <item type="action" callTarget="instance" callName="setPosition" target="baZii">
      <item valueDataType="any" value="435.79" name="16"/>
      <item valueDataType="any" value="341.22" name="17"/>
    </item>
    <item type="action" callTarget="instance" callName="setPosition" target="drawRe">
      <item valueDataType="any" value="365" name="16"/>
      <item valueDataType="any" value="304" name="17"/>
    </item>
    <item type="action" callTarget="instance" callName="rotateClockWise" target="drawRe">
      <item valueDataType="any" value="120" name="10"/>
    </item>
    <item type="action" callTarget="instance" callName="destory" target="TT4"/>
    <item type="action" callTarget="instance" callName="setEnabled" target="TT5">
      <item valueDataType="any" value="1" name="14"/>
    </item>
  </item>
  <item type="event" conditionRelationShip="true" triggerOnceWhileTrue="false">
    <item type="condition" callTarget="instance" paramsClass="IsButtonDownEvent" callName="isTouchDown" isTrigger="false" target="TT5"/>
    <item type="action" callTarget="instance" callName="play" target="TouchDown">
      <item valueDataType="any" value="1" name="2"/>
      <item valueDataType="any" value="1" name="3"/>
    </item>
    <item type="action" callTarget="instance" callName="setValue" target="pane">
      <item valueDataType="string" value="one" name="10" variable="true"/>
      <item valueDataType="any" value="5" name="11"/>
    </item>
    <item type="action" callTarget="instance" callName="setPosition" target="baZii">
      <item valueDataType="any" value="365.74" name="16"/>
      <item valueDataType="any" value="359.22" name="17"/>
    </item>
    <item type="action" callTarget="instance" callName="setPosition" target="drawRf">
      <item valueDataType="any" value="400" name="16"/>
      <item valueDataType="any" value="350" name="17"/>
    </item>
    <item type="action" callTarget="instance" callName="rotateCounterClockWise" target="drawRf">
      <item valueDataType="any" value="100" name="11"/>
    </item>
    <item type="action" callTarget="instance" callName="destory" target="TT5"/>
    <item type="action" callTarget="instance" callName="setPosition" target="F4">
      <item valueDataType="any" value="435.79" name="16"/>
      <item valueDataType="any" value="341.22" name="17"/>
    </item>
    <item type="action" callTarget="instance" callName="setEnabled" target="TT6">
      <item valueDataType="any" value="1" name="14"/>
    </item>
  </item>
  <item type="event" conditionRelationShip="true" triggerOnceWhileTrue="false">
    <item type="condition" callTarget="instance" paramsClass="IsButtonDownEvent" callName="isTouchDown" isTrigger="false" target="TT6"/>
    <item type="action" callTarget="instance" callName="play" target="TouchDown">
      <item valueDataType="any" value="1" name="2"/>
      <item valueDataType="any" value="1" name="3"/>
    </item>
    <item type="action" callTarget="instance" callName="setValue" target="pane">
      <item valueDataType="string" value="one" name="10" variable="true"/>
      <item valueDataType="any" value="6" name="11"/>
    </item>
    <item type="action" callTarget="instance" callName="destory" target="baZii"/>
    <item type="action" callTarget="instance" callName="setPosition" target="Bears">
      <item valueDataType="any" value="331.68" name="16"/>
      <item valueDataType="any" value="292.00" name="17"/>
    </item>
    <item type="action" callTarget="instance" callName="setVisible" target="textA">
      <item valueDataType="any" value="1" name="10"/>
    </item>
    <item type="action" callTarget="instance" callName="setVisible" target="textB">
      <item valueDataType="any" value="1" name="10"/>
    </item>
    <item type="action" callTarget="instance" callName="setVisible" target="textD">
      <item valueDataType="any" value="1" name="10"/>
    </item>
    <item type="action" callTarget="instance" callName="setVisible" target="textC">
      <item valueDataType="any" value="1" name="10"/>
    </item>
    <item type="action" callTarget="instance" callName="rotateCounterClockWise" target="drawQ">
      <item valueDataType="any" value="80" name="11"/>
    </item>
    <item type="action" callTarget="instance" callName="setPosition" target="drawQ">
      <item valueDataType="any" value="330" name="16"/>
      <item valueDataType="any" value="350" name="17"/>
    </item>
    <item type="action" callTarget="instance" callName="setPosition" target="F5">
      <item valueDataType="any" value="365.74" name="16"/>
      <item valueDataType="any" value="359.22" name="17"/>
    </item>
    <item type="action" callTarget="instance" callName="destory" target="TT6"/>
    <item type="action" callTarget="instance" callName="execTween" target="nextBtn">
      <item valueDataType="any" value="nextBtn" name="key"/>
      <item valueDataType="any" value="638.69" name="x"/>
      <item valueDataType="any" value="358.05" name="y"/>
      <item valueDataType="any" value="" name="anchorX"/>
      <item valueDataType="any" value="" name="anchorY"/>
      <item valueDataType="any" value="" name="width"/>
      <item valueDataType="any" value="" name="height"/>
      <item valueDataType="any" value="" name="rotation"/>
      <item valueDataType="any" value="" name="alpha"/>
      <item valueDataType="any" value="1000" name="duration"/>
      <item valueDataType="string" value="bounceInOut" name="ease"/>
      <item valueDataType="any" value="0" name="waitTime"/>
      <item valueDataType="any" value="0" name="loop"/>
      <item valueDataType="any" value="1" name="scaleX"/>
      <item valueDataType="any" value="1" name="scaleY"/>
    </item>
  </item>
  <item type="event" conditionRelationShip="true" triggerOnceWhileTrue="false">
    <item type="condition" callTarget="instance" paramsClass="IsButtonDownEvent" callName="isTouchDown" isTrigger="false" target="nextBtn"/>
    <item type="action" callTarget="instance" callName="play" target="TouchDown">
      <item valueDataType="any" value="1" name="2"/>
      <item valueDataType="any" value="1" name="3"/>
    </item>
    <item type="action" callTarget="instance" callName="gotoScene" target="System">
      <item valueDataType="any" value="newScene1" name="18"/>
    </item>
  </item>
  <item type="event" conditionRelationShip="true" triggerOnceWhileTrue="false">
    <item type="condition" callTarget="instance" paramsClass="OnButtonBeginEvent" callName="onButtonBegin" isTrigger="true" target="baZii"/>
    <item type="action" callTarget="instance" callName="gotoScene" target="System">
      <item valueDataType="any" value="MainScene" name="18"/>
    </item>
  </item>
  <item type="event" conditionRelationShip="true" triggerOnceWhileTrue="false">
    <item type="condition" callTarget="instance" paramsClass="OnButtonBeginEvent" callName="onButtonBegin" isTrigger="true" target="resBTn"/>
    <item type="action" callTarget="instance" callName="reload" target="Browser"/>
  </item>
</eventSheets>